lephare/__init__.py
lephare/_flt.py
lephare/_lephare.cpython-311-x86_64-linux-gnu.so
lephare/_pdf.py
lephare/_photoz.py
lephare/_plot_utils.py
lephare/_spec.py
lephare/_utils.py
lephare/_version.py
lephare/data_manager.py
lephare/data_retrieval.py
lephare/default_cosmos_config.py
lephare/filter.py
lephare/filterSvc.py
lephare/filter_extinc.py
lephare/magSvc.py
lephare/mag_gal.py
lephare/prepare.py
lephare/process.py
lephare/runner.py
lephare/sedtolib.py
lephare/zphota.py
lephare.libs/libgomp-a34b3233.so.1.0.0
lib/Makefile
lib/PDF.cpp
lib/PDF.h
lib/SED.cpp
lib/SED.h
lib/SEDLib.cpp
lib/SEDLib.h
lib/_bindings.cc
lib/cosmology.cpp
lib/cosmology.h
lib/ext.cpp
lib/ext.h
lib/ext_curv.cpp
lib/filter.cpp
lib/filter_extinc.cpp
lib/flt.cpp
lib/flt.h
lib/globals.cpp
lib/globals.h
lib/keyword.cpp
lib/keyword.h
lib/mag.cpp
lib/mag.h
lib/mag_gal.cpp
lib/oneElLambda.cpp
lib/oneElLambda.h
lib/onesource.cpp
lib/onesource.h
lib/opa.cpp
lib/opa.h
lib/photoz_lib.cpp
lib/photoz_lib.h
lib/sedtolib.cpp
lib/zphota.cpp
lephare-0.3.0.dist-info/METADATA
lephare-0.3.0.dist-info/WHEEL
lephare-0.3.0.dist-info/entry_points.txt
lephare-0.3.0.dist-info/top_level.txt
lephare-0.3.0.dist-info/RECORD
lephare-0.3.0.dist-info/licenses/LICENSE
