Metadata-Version: 2.4
Name: lephare
Version: 0.3.0
Summary: LEPHARE photometric redshift estimator
Home-page: https://lephare.readthedocs.io/en/latest/
Author-email: Stéphane Arnouts <stephane.arnouts@lam.fr>, Olivier Ilbert <olivier.ilbert@lam.fr>, Johann Cohen-Tanugi <johann.cohen-tanugi@in2p3.fr>, Raphael Shirley <rshirley@mpe.mpg.de>
License: MIT License
Project-URL: Source Code, https://github.com/lephare-photoz/lephare
Classifier: Development Status :: 4 - Beta
Classifier: License :: OSI Approved :: MIT License
Classifier: Intended Audience :: Developers
Classifier: Intended Audience :: Science/Research
Classifier: Operating System :: OS Independent
Classifier: Programming Language :: Python
Classifier: Programming Language :: C++
Requires-Python: >=3.9
License-File: LICENSE
Requires-Dist: matplotlib
Requires-Dist: numpy
Requires-Dist: astropy
Requires-Dist: scipy
Requires-Dist: requests
Requires-Dist: pooch
Requires-Dist: platformdirs
Requires-Dist: wurlitzer
Provides-Extra: dev
Requires-Dist: jupyter; extra == "dev"
Requires-Dist: pre-commit; extra == "dev"
Requires-Dist: pytest; extra == "dev"
Requires-Dist: pytest-cov; extra == "dev"
Requires-Dist: ruff; extra == "dev"
Requires-Dist: sphinx; extra == "dev"
Requires-Dist: sphinx-tabs; extra == "dev"
Requires-Dist: breathe; extra == "dev"
Requires-Dist: exhale; extra == "dev"
Dynamic: home-page
Dynamic: license-file
Dynamic: requires-python
